collecting_faces/__init__.py
collecting_faces/collect_faces.py
collecting_faces/main.py
collecting_faces/preprocess/__init__.py
collecting_faces/preprocess/align_images.py
collecting_faces/preprocess/face_alignment.py
collecting_faces/preprocess/landmarks_detector.py
collecting_faces/preprocess/shape_predictor_68_face_landmarks.dat
collecting_faces/preprocess/unpack_bz2.py
collecting_faces-1.0.5.dist-info/LICENSE
collecting_faces-1.0.5.dist-info/METADATA
collecting_faces-1.0.5.dist-info/WHEEL
collecting_faces-1.0.5.dist-info/top_level.txt
collecting_faces-1.0.5.dist-info/RECORD
