Metadata-Version: 2.1
Name: collecting-faces
Version: 1.0.5
Summary: Collecting square faces from images for training stylegan2-ada
Home-page: https://github.com/Seokhee-Jin/collecting_faces
Author: Seokhee-Jin
Author-email: seokhee749@gmail.com
Classifier: Programming Language :: Python :: 3
Classifier: License :: OSI Approved :: MIT License
Classifier: Operating System :: OS Independent
Requires-Python: >=3.6
License-File: LICENSE
Requires-Dist: dlib
Requires-Dist: numpy
Requires-Dist: opencv-python
Requires-Dist: Pillow
Requires-Dist: scipy
Requires-Dist: tqdm
